uptimecurl-0.1.5.dist-info/METADATA
uptimecurl-0.1.5.dist-info/WHEEL
uptimecurl-0.1.5.dist-info/entry_points.txt
uptimecurl-0.1.5.dist-info/licenses/COPYING
uptimecurl-0.1.5.dist-info/licenses/LICENSES/AGPL-3.0-or-later.txt
uptimecurl-0.1.5.dist-info/licenses/LICENSES/CC-BY-4.0.txt
uptimecurl-0.1.5.dist-info/licenses/LICENSES/CC-BY-SA-4.0.txt
uptimecurl-0.1.5.dist-info/licenses/LICENSES/CC0-1.0.txt
uptimecurl-0.1.5.dist-info/licenses/LICENSES/LicenseRef-DCO-1.1-license.txt
uptimecurl/__init__.py
uptimecurl/definition.yaml
uptimecurl/definition.yaml.license
uptimecurl/template.mustache
uptimecurl/template.mustache.license
uptimecurl/uptimecurl.py
uptimecurl-0.1.5.dist-info/RECORD
