Metadata-Version: 2.1
Name: uptimecurl
Version: 0.1.5
Summary: Basic monitoring tool designed for rapid deployment and simple results.
Author-Email: David Seaward <david@librem.one>
License: AGPL-3.0-or-later
Project-URL: Source, https://gitlab.com/lfdo/uptimecurl
Project-URL: Project, https://lofidevops.neocities.org
Requires-Python: >=3.10
Requires-Dist: chevron>=0.13
Requires-Dist: click>=8.1.3
Requires-Dist: python-dotenv>=0.14
Requires-Dist: requests>=2.24
Requires-Dist: ruamel-yaml>=0.17.21
